imagepills/__init__.py
imagepills/base.py
imagepills/entrypoint.py
imagepills/imagepills.py
imagepills/pills.py
imagepills/utils.py
imagepills-0.0.6.dist-info/LICENSE
imagepills-0.0.6.dist-info/METADATA
imagepills-0.0.6.dist-info/WHEEL
imagepills-0.0.6.dist-info/entry_points.txt
imagepills-0.0.6.dist-info/top_level.txt
imagepills-0.0.6.dist-info/RECORD
