Metadata-Version: 2.1
Name: imagepills
Version: 0.0.6
Summary: imagepills is a package that provides high level abstraction for some image utilities
Home-page: https://github.com/maekind/imagepills
Author: Marco Espinosa
Author-email: marco@marcoespinosa.es
License: MIT
Classifier: Development Status :: 5 - Production/Stable
Classifier: Intended Audience :: Developers
Classifier: License :: OSI Approved :: MIT License
Classifier: Operating System :: OS Independent
Classifier: Programming Language :: Python :: 3
Classifier: Programming Language :: Python :: 3 :: Only
Classifier: Programming Language :: Python :: 3.9
Classifier: Programming Language :: Python :: 3.10
Classifier: Programming Language :: Python :: 3.11
Classifier: Environment :: Console
Classifier: Topic :: Utilities
Requires-Python: >=3.9
License-File: LICENSE
